{"stats":{"minecraft:picked_up":{"minecraft:prismarine_shard":21,"minecraft:smithing_table":1,"minecraft:diamond_sword":10,"minecraft:oak_stairs":10,"minecraft:golden_shovel":1,"minecraft:enchanted_book":4,"minecraft:brewing_stand":2,"minecraft:polished_blackstone_brick_stairs":1,"minecraft:string":95,"minecraft:pufferfish":4,"minecraft:beetroot":116,"minecraft:diamond_leggings":2,"minecraft:cobbled_deepslate":567,"minecraft:spruce_planks":30,"minecraft:melon_slice":286,"minecraft:acacia_log":3,"minecraft:cauldron":1,"minecraft:stone_sword":6,"minecraft:tropical_fish":3,"minecraft:bookshelf":1,"minecraft:blaze_rod":3,"minecraft:iron_bars":51,"minecraft:birch_log":4,"minecraft:feather":138,"minecraft:cooked_beef":63,"minecraft:iron_door":9,"minecraft:birch_slab":44,"minecraft:water_bucket":3,"minecraft:jungle_log":181,"minecraft:brown_wool":1,"minecraft:flint":65,"minecraft:chipped_anvil":1,"minecraft:stonecutter":2,"minecraft:diamond_helmet":3,"minecraft:glowstone_dust":9,"minecraft:birch_fence_gate":2,"minecraft:dark_oak_log":3,"minecraft:granite":127,"minecraft:bread":32,"minecraft:dark_oak_fence":3,"minecraft:diamond_pickaxe":11,"minecraft:crafting_table":30,"minecraft:leather_leggings":1,"minecraft:elytra":2,"minecraft:red_bed":1,"minecraft:flint_and_steel":2,"minecraft:white_carpet":8,"minecraft:iron_shovel":5,"minecraft:music_disc_otherside":3,"minecraft:beef":345,"minecraft:poppy":1,"minecraft:jungle_sapling":1,"minecraft:iron_nugget":6,"minecraft:minecart":6,"minecraft:chest":6,"minecraft:birch_sapling":1,"minecraft:egg":513,"minecraft:sandstone":36,"minecraft:stone":29,"minecraft:oak_door":14,"minecraft:spruce_fence":1,"minecraft:fire_charge":1,"minecraft:carrot":440,"minecraft:redstone":393,"minecraft:prismarine_crystals":7,"minecraft:diamond_chestplate":5,"minecraft:beetroot_seeds":320,"minecraft:shears":7,"minecraft:diamond_boots":3,"minecraft:hay_block":7,"minecraft:gold_ingot":4,"minecraft:totem_of_undying":1,"minecraft:mutton":8,"minecraft:white_wool":95,"minecraft:rail":39,"minecraft:tripwire_hook":1,"minecraft:filled_map":2,"minecraft:oak_log":92,"minecraft:ancient_debris":64,"minecraft:lily_pad":1,"minecraft:paper":20,"minecraft:white_banner":13,"minecraft:birch_pressure_plate":1,"minecraft:stone_bricks":184,"minecraft:apple":16,"minecraft:kelp":7,"minecraft:oak_fence_gate":1,"minecraft:glass_bottle":9,"minecraft:iron_sword":1,"minecraft:dark_oak_stairs":16,"minecraft:smooth_basalt":7,"minecraft:gravel":338,"minecraft:birch_stairs":93,"minecraft:spruce_log":1,"minecraft:diamond_shovel":1,"minecraft:tide_armor_trim_smithing_template":1,"minecraft:diamond_axe":3,"minecraft:baked_potato":24,"minecraft:melon_seeds":19,"minecraft:stripped_dark_oak_log":1,"minecraft:hopper":16,"minecraft:ender_pearl":3717,"minecraft:black_carpet":9,"minecraft:wheat":237,"minecraft:nether_brick_fence":4,"minecraft:yellow_wool":7,"minecraft:potion":8,"minecraft:raw_copper":5,"minecraft:iron_leggings":1,"minecraft:oak_sign":3,"minecraft:bucket":2,"minecraft:redstone_torch":51,"minecraft:iron_pickaxe":2,"minecraft:iron_boots":3,"minecraft:stick":65,"minecraft:acacia_fence":2,"minecraft:birch_trapdoor":3,"minecraft:oak_fence":19,"minecraft:torch":247,"minecraft:spruce_stairs":12,"minecraft:porkchop":17,"minecraft:pointed_dripstone":3,"minecraft:diorite":121,"minecraft:rotten_flesh":86,"minecraft:obsidian":20,"minecraft:cod":36,"minecraft:cobblestone":3466,"minecraft:enchanting_table":1,"minecraft:pink_petals":4,"minecraft:lilac":6,"minecraft:magma_cream":1,"minecraft:andesite":92,"minecraft:golden_leggings":2,"minecraft:potato":1,"minecraft:tuff":34,"minecraft:prismarine_bricks":23,"minecraft:dirt":4830,"minecraft:lapis_lazuli":786,"minecraft:name_tag":27,"minecraft:glass":108,"minecraft:bone":89,"minecraft:orange_tulip":1,"minecraft:bow":6,"minecraft:wheat_seeds":752,"minecraft:cobbled_deepslate_wall":6,"minecraft:grindstone":2,"minecraft:mossy_stone_bricks":1,"minecraft:bamboo":528,"minecraft:powered_rail":6,"minecraft:prismarine":11,"minecraft:oak_planks":90,"minecraft:cooked_porkchop":4,"minecraft:oak_pressure_plate":4,"minecraft:sand":640,"minecraft:jungle_planks":381,"minecraft:grass_block":4,"minecraft:jungle_slab":1,"minecraft:shulker_box":2,"minecraft:mossy_cobblestone":44,"minecraft:dark_prismarine":9,"minecraft:jungle_leaves":13,"minecraft:yellow_carpet":7,"minecraft:diamond":396,"minecraft:cracked_polished_blackstone_bricks":5,"minecraft:crossbow":1,"minecraft:golden_apple":2,"minecraft:emerald":8,"minecraft:oak_sapling":22,"minecraft:netherrack":960,"minecraft:chorus_fruit":60,"minecraft:oak_leaves":5,"minecraft:fishing_rod":1,"minecraft:cocoa_beans":62,"minecraft:chicken":149,"minecraft:ladder":22,"minecraft:chest_minecart":3,"minecraft:wooden_pickaxe":1,"minecraft:gold_block":16,"minecraft:chain":5,"minecraft:iron_axe":3,"minecraft:item_frame":1,"minecraft:birch_fence":10,"minecraft:blackstone":157,"minecraft:detector_rail":4,"minecraft:oak_boat":31,"minecraft:light_gray_wool":7,"minecraft:sugar_cane":4,"minecraft:phantom_membrane":4,"minecraft:raw_iron":342,"minecraft:end_stone":73,"minecraft:polished_blackstone_bricks":4,"minecraft:stone_button":10,"minecraft:stone_pressure_plate":2,"minecraft:dark_oak_planks":28,"minecraft:arrow":81,"minecraft:pumpkin_pie":71,"minecraft:jungle_stairs":1,"minecraft:nether_bricks":24,"minecraft:saddle":5,"minecraft:wet_sponge":12,"minecraft:basalt":1477,"minecraft:glow_ink_sac":5,"minecraft:salmon":14,"minecraft:leather":216,"minecraft:birch_planks":542,"minecraft:gunpowder":49,"minecraft:cobblestone_stairs":17,"minecraft:cooked_mutton":3,"minecraft:iron_ingot":20,"minecraft:cooked_chicken":74,"minecraft:book":3,"minecraft:scaffolding":6,"minecraft:oak_slab":138,"minecraft:pumpkin":13,"minecraft:birch_boat":5,"minecraft:chiseled_stone_bricks":143,"minecraft:stone_brick_slab":4,"minecraft:quartz":21,"minecraft:dandelion":1,"minecraft:dripstone_block":4,"minecraft:spider_eye":7,"minecraft:pumpkin_seeds":6,"minecraft:iron_helmet":9,"minecraft:black_wool":4,"minecraft:coal":557},"minecraft:broken":{"minecraft:stone_hoe":1,"minecraft:iron_axe":1,"minecraft:iron_pickaxe":2,"minecraft:golden_shovel":1,"minecraft:stone_axe":1,"minecraft:golden_hoe":1},"minecraft:killed_by":{"minecraft:zombie":2,"minecraft:vex":1,"minecraft:guardian":1,"minecraft:creeper":1,"minecraft:cave_spider":1,"minecraft:endermite":1,"minecraft:spider":1,"minecraft:enderman":9},"minecraft:crafted":{"minecraft:oak_sign":3,"minecraft:birch_slab":414,"minecraft:diamond_shovel":2,"minecraft:bookshelf":18,"minecraft:cooked_mutton":2,"minecraft:glass":248,"minecraft:diamond_helmet":2,"minecraft:diamond_leggings":2,"minecraft:birch_fence_gate":1,"minecraft:iron_door":3,"minecraft:cooked_porkchop":45,"minecraft:diamond_axe":1,"minecraft:cobbled_deepslate_wall":36,"minecraft:copper_ingot":3,"minecraft:cartography_table":1,"minecraft:stone_slab":6,"minecraft:iron_pickaxe":4,"minecraft:iron_block":20,"minecraft:netherite_ingot":16,"minecraft:birch_stairs":432,"minecraft:prismarine":2,"minecraft:diamond_hoe":1,"minecraft:bone_meal":15,"minecraft:white_carpet":135,"minecraft:stone_pickaxe":3,"minecraft:diamond_boots":2,"minecraft:enchanting_table":1,"minecraft:oak_fence_gate":1,"minecraft:golden_apple":7,"minecraft:birch_trapdoor":2,"minecraft:iron_leggings":1,"minecraft:grindstone":1,"minecraft:oak_planks":504,"minecraft:cobblestone_slab":6,"minecraft:cooked_chicken":115,"minecraft:stone":3,"minecraft:hopper":5,"minecraft:bow":2,"minecraft:iron_boots":1,"minecraft:chest":16,"minecraft:chiseled_stone_bricks":94,"minecraft:stone_hoe":1,"minecraft:oak_fence":54,"minecraft:item_frame":3,"minecraft:crafting_table":4,"minecraft:wooden_pickaxe":2,"minecraft:baked_potato":42,"minecraft:iron_helmet":1,"minecraft:birch_pressure_plate":2,"minecraft:birch_planks":460,"minecraft:book":42,"minecraft:iron_chestplate":1,"minecraft:charcoal":3,"minecraft:diamond_pickaxe":3,"minecraft:shield":1,"minecraft:birch_fence":24,"minecraft:stick":128,"minecraft:iron_ingot":348,"minecraft:light_gray_carpet":9,"minecraft:fishing_rod":1,"minecraft:furnace":8,"minecraft:iron_axe":1,"minecraft:iron_hoe":1,"minecraft:netherite_scrap":64,"minecraft:birch_sign":6,"minecraft:cooked_beef":161,"minecraft:cooked_cod":32,"minecraft:diamond_sword":2,"minecraft:yellow_carpet":9,"minecraft:iron_sword":1,"minecraft:cooked_salmon":11,"minecraft:bread":24,"minecraft:air":0,"minecraft:jungle_planks":888,"minecraft:oak_boat":3,"minecraft:black_carpet":15,"minecraft:anvil":5,"minecraft:acacia_planks":8,"minecraft:diamond_chestplate":2},"minecraft:killed":{"minecraft:cave_spider":11,"minecraft:cod":10,"minecraft:skeleton":127,"minecraft:guardian":38,"minecraft:chicken":138,"minecraft:tropical_fish":2,"minecraft:magma_cube":16,"minecraft:elder_guardian":3,"minecraft:pillager":39,"minecraft:donkey":1,"minecraft:zombie":359,"minecraft:glow_squid":2,"minecraft:cow":135,"minecraft:evoker":1,"minecraft:vindicator":6,"minecraft:endermite":1,"minecraft:ravager":2,"minecraft:enderman":7620,"minecraft:witch":10,"minecraft:spider":57,"minecraft:silverfish":3,"minecraft:piglin_brute":6,"minecraft:wolf":1,"minecraft:piglin":2,"minecraft:pig":6,"minecraft:zombie_villager":1,"minecraft:creeper":32,"minecraft:sheep":5,"minecraft:blaze":15,"minecraft:phantom":47,"minecraft:drowned":2,"minecraft:bat":3},"minecraft:custom":{"minecraft:interact_with_crafting_table":157,"minecraft:open_barrel":6,"minecraft:bell_ring":41,"minecraft:leave_game":27,"minecraft:time_since_death":328384,"minecraft:damage_blocked_by_shield":348,"minecraft:play_time":2070814,"minecraft:deaths":26,"minecraft:jump":20435,"minecraft:enchant_item":74,"minecraft:interact_with_furnace":476,"minecraft:play_record":3,"minecraft:interact_with_cartography_table":7,"minecraft:sleep_in_bed":14,"minecraft:damage_dealt":150929,"minecraft:interact_with_smoker":1,"minecraft:horse_one_cm":2821563,"minecraft:interact_with_smithing_table":4,"minecraft:interact_with_anvil":22,"minecraft:inspect_hopper":56,"minecraft:sneak_time":94435,"minecraft:interact_with_blast_furnace":13,"minecraft:total_world_time":2070814,"minecraft:interact_with_stonecutter":11,"minecraft:time_since_rest":227053,"minecraft:swim_one_cm":839499,"minecraft:fly_one_cm":3586849,"minecraft:open_chest":1314,"minecraft:fish_caught":41,"minecraft:fall_one_cm":447517,"minecraft:animals_bred":174,"minecraft:open_shulker_box":55,"minecraft:sprint_one_cm":4550555,"minecraft:drop":874,"minecraft:talked_to_villager":9,"minecraft:interact_with_brewingstand":4,"minecraft:walk_on_water_one_cm":306194,"minecraft:player_kills":2,"minecraft:crouch_one_cm":288530,"minecraft:mob_kills":8728,"minecraft:fill_cauldron":1,"minecraft:interact_with_campfire":7,"minecraft:climb_one_cm":25897,"minecraft:walk_one_cm":8937941,"minecraft:raid_win":1,"minecraft:walk_under_water_one_cm":491024,"minecraft:boat_one_cm":5047564,"minecraft:raid_trigger":1,"minecraft:interact_with_grindstone":33,"minecraft:damage_taken":26851,"minecraft:damage_absorbed":134,"minecraft:minecart_one_cm":6},"minecraft:dropped":{"minecraft:iron_sword":1,"minecraft:cooked_beef":70,"minecraft:chorus_fruit":60,"minecraft:crafting_table":26,"minecraft:cooked_porkchop":18,"minecraft:orange_tulip":1,"minecraft:rail":81,"minecraft:leather_helmet":4,"minecraft:dirt":3523,"minecraft:stone_button":9,"minecraft:dark_oak_fence":3,"minecraft:chain":5,"minecraft:wooden_sword":1,"minecraft:phantom_membrane":1,"minecraft:sand":165,"minecraft:iron_pickaxe":2,"minecraft:dark_oak_planks":28,"minecraft:white_wool":1,"minecraft:bone":68,"minecraft:oak_door":2,"minecraft:iron_nugget":6,"minecraft:cooked_chicken":61,"minecraft:detector_rail":6,"minecraft:cobbled_deepslate":573,"minecraft:black_carpet":18,"minecraft:obsidian":2,"minecraft:stripped_dark_oak_log":1,"minecraft:rotten_flesh":79,"minecraft:oak_planks":38,"minecraft:nether_brick_fence":4,"minecraft:jungle_stairs":1,"minecraft:leather_boots":5,"minecraft:ladder":1,"minecraft:leather_leggings":4,"minecraft:egg":2,"minecraft:wheat_seeds":4,"minecraft:dripstone_block":4,"minecraft:cobbled_deepslate_wall":4,"minecraft:oak_fence":3,"minecraft:iron_helmet":5,"minecraft:cobblestone":2128,"minecraft:granite":122,"minecraft:yellow_carpet":9,"minecraft:coal":11,"minecraft:golden_apple":5,"minecraft:pufferfish":4,"minecraft:jungle_slab":1,"minecraft:wooden_axe":1,"minecraft:oak_stairs":9,"minecraft:string":70,"minecraft:lily_pad":1,"minecraft:stone_sword":2,"minecraft:white_carpet":6,"minecraft:iron_boots":3,"minecraft:name_tag":12,"minecraft:nether_bricks":13,"minecraft:diamond_sword":1,"minecraft:stone":62,"minecraft:spruce_planks":29,"minecraft:diamond_pickaxe":6,"minecraft:redstone_torch":51,"minecraft:stone_pressure_plate":2,"minecraft:spider_eye":7,"minecraft:stone_bricks":14,"minecraft:bamboo":16,"minecraft:birch_boat":1,"minecraft:sandstone":30,"minecraft:bow":2,"minecraft:dark_prismarine":9,"minecraft:birch_planks":56,"minecraft:dark_oak_stairs":16,"minecraft:diamond_axe":3,"minecraft:baked_potato":12,"minecraft:ender_pearl":3125,"minecraft:chest_minecart":3,"minecraft:leather":14,"minecraft:jungle_planks":152,"minecraft:flint":65,"minecraft:cracked_polished_blackstone_bricks":5,"minecraft:dark_oak_log":3,"minecraft:polished_blackstone_brick_stairs":1,"minecraft:mutton":1,"minecraft:pumpkin_pie":40,"minecraft:polished_blackstone_bricks":4,"minecraft:gravel":390,"minecraft:blackstone":72,"minecraft:yellow_wool":1,"minecraft:pointed_dripstone":3,"minecraft:beetroot":1,"minecraft:diamond_shovel":1,"minecraft:prismarine":6,"minecraft:poppy":1,"minecraft:leather_chestplate":1,"minecraft:gunpowder":5,"minecraft:beetroot_seeds":6,"minecraft:basalt":785,"minecraft:iron_bars":9,"minecraft:arrow":12,"minecraft:powered_rail":6,"minecraft:prismarine_bricks":20,"minecraft:scaffolding":6,"minecraft:oak_leaves":3,"minecraft:netherrack":221,"minecraft:bread":29,"minecraft:lilac":6,"minecraft:minecart":1,"minecraft:prismarine_shard":1,"minecraft:spruce_stairs":12,"minecraft:acacia_log":1,"minecraft:grass_block":7,"minecraft:stick":8,"minecraft:diorite":123,"minecraft:torch":33,"minecraft:melon_slice":6,"minecraft:brown_wool":1,"minecraft:iron_leggings":1,"minecraft:jungle_leaves":7,"minecraft:pink_petals":4,"minecraft:redstone":36,"minecraft:kelp":7,"minecraft:raw_copper":5,"minecraft:tuff":34,"minecraft:light_gray_wool":1,"minecraft:filled_map":3,"minecraft:diamond_chestplate":3,"minecraft:andesite":59,"minecraft:oak_sapling":6,"minecraft:spruce_log":1,"minecraft:wooden_pickaxe":3,"minecraft:magma_cream":1,"minecraft:nautilus_shell":1},"minecraft:used":{"minecraft:beetroot":4,"minecraft:ladder":10,"minecraft:elytra":1,"minecraft:black_carpet":6,"minecraft:chest":17,"minecraft:stone":1,"minecraft:cocoa_beans":4,"minecraft:jungle_sapling":1,"minecraft:music_disc_pigstep":1,"minecraft:birch_sapling":1,"minecraft:bow":559,"minecraft:oak_sapling":9,"minecraft:furnace":8,"minecraft:cooked_cod":32,"minecraft:acacia_fence":3,"minecraft:egg":606,"minecraft:mossy_stone_bricks":1,"minecraft:diorite":13,"minecraft:prismarine":7,"minecraft:blackstone":5,"minecraft:wooden_pickaxe":28,"minecraft:oak_leaves":130,"minecraft:golden_apple":4,"minecraft:glow_berries":3,"minecraft:sand":18,"minecraft:pumpkin_seeds":10,"minecraft:birch_fence":34,"minecraft:birch_slab":457,"minecraft:oak_pressure_plate":4,"minecraft:lilac":14,"minecraft:diamond_sword":4397,"minecraft:smithing_table":1,"minecraft:oak_boat":23,"minecraft:iron_bars":1,"minecraft:enchanting_table":2,"minecraft:light_gray_carpet":9,"minecraft:cooked_salmon":11,"minecraft:netherrack":34,"minecraft:torch":20,"minecraft:brewing_stand":2,"minecraft:anvil":6,"minecraft:yellow_carpet":9,"minecraft:golden_shovel":35,"minecraft:oak_fence_gate":2,"minecraft:chipped_anvil":1,"minecraft:iron_axe":473,"minecraft:totem_of_undying":1,"minecraft:melon_seeds":23,"minecraft:smooth_basalt":7,"minecraft:bamboo":57,"minecraft:diamond_chestplate":4,"minecraft:basalt":64,"minecraft:beef":2,"minecraft:cobbled_deepslate":198,"minecraft:wheat_seeds":472,"minecraft:water_bucket":440,"minecraft:birch_planks":862,"minecraft:cartography_table":1,"minecraft:cauldron":1,"minecraft:rail":1,"minecraft:oak_slab":138,"minecraft:crafting_table":6,"minecraft:red_bed":1,"minecraft:birch_sign":4,"minecraft:cod":5,"minecraft:diamond_pickaxe":12862,"minecraft:diamond_shovel":10891,"minecraft:iron_pickaxe":969,"minecraft:chiseled_stone_bricks":453,"minecraft:cobblestone":1461,"minecraft:potion":3,"minecraft:cooked_porkchop":27,"minecraft:dandelion":1,"minecraft:diamond_leggings":2,"minecraft:diamond_hoe":464,"minecraft:oak_sign":6,"minecraft:shield":6,"minecraft:iron_sword":79,"minecraft:birch_pressure_plate":3,"minecraft:jungle_planks":874,"minecraft:nether_bricks":11,"minecraft:carrot":200,"minecraft:obsidian":14,"minecraft:glass":399,"minecraft:iron_helmet":1,"minecraft:stone_bricks":168,"minecraft:item_frame":4,"minecraft:birch_trapdoor":5,"minecraft:hay_block":7,"minecraft:beetroot_seeds":197,"minecraft:diamond_boots":2,"minecraft:stone_pickaxe":186,"minecraft:oak_planks":94,"minecraft:ender_pearl":102,"minecraft:sugar_cane":4,"minecraft:diamond_axe":1477,"minecraft:golden_hoe":32,"minecraft:crossbow":71,"minecraft:end_stone":73,"minecraft:birch_fence_gate":3,"minecraft:melon_slice":40,"minecraft:bread":45,"minecraft:iron_door":8,"minecraft:grindstone":3,"minecraft:andesite":48,"minecraft:bone_meal":9,"minecraft:experience_bottle":4,"minecraft:oak_fence":70,"minecraft:rose_bush":14,"minecraft:music_disc_otherside":2,"minecraft:flint_and_steel":9,"minecraft:tropical_fish":1,"minecraft:stone_hoe":131,"minecraft:cooked_chicken":112,"minecraft:oak_door":9,"minecraft:dirt":1373,"minecraft:white_carpet":140,"minecraft:hopper":21,"minecraft:prismarine_bricks":3,"minecraft:diamond_helmet":4,"minecraft:shulker_box":1,"minecraft:bee_nest":1,"minecraft:spruce_fence":1,"minecraft:granite":25,"minecraft:iron_hoe":45,"minecraft:stone_brick_slab":4,"minecraft:wooden_axe":38,"minecraft:bookshelf":19,"minecraft:iron_boots":1,"minecraft:cooked_beef":123,"minecraft:pumpkin":13,"minecraft:iron_leggings":1,"minecraft:cobbled_deepslate_wall":36,"minecraft:cooked_mutton":9,"minecraft:cobblestone_stairs":17,"minecraft:baked_potato":21,"minecraft:birch_boat":1,"minecraft:stonecutter":2,"minecraft:apple":13,"minecraft:map":2,"minecraft:stone_axe":26,"minecraft:fishing_rod":55,"minecraft:white_banner":7,"minecraft:bucket":443,"minecraft:pumpkin_pie":30,"minecraft:birch_stairs":515},"minecraft:mined":{"minecraft:dark_oak_planks":35,"minecraft:jungle_leaves":14,"minecraft:obsidian":16,"minecraft:granite":138,"minecraft:acacia_log":3,"minecraft:yellow_carpet":6,"minecraft:jungle_log":199,"minecraft:oak_pressure_plate":2,"minecraft:hopper":12,"minecraft:oak_wall_sign":3,"minecraft:chiseled_stone_bricks":46,"minecraft:spawner":13,"minecraft:polished_blackstone_bricks":4,"minecraft:tall_seagrass":16,"minecraft:magma_block":32,"minecraft:cobbled_deepslate":37,"minecraft:fire":31,"minecraft:pumpkin":13,"minecraft:deepslate_lapis_ore":69,"minecraft:enchanting_table":1,"minecraft:water_cauldron":1,"minecraft:dirt_path":10,"minecraft:oak_stairs":1,"minecraft:white_banner":1,"minecraft:red_bed":1,"minecraft:kelp_plant":5,"minecraft:powder_snow":3,"minecraft:torch":6,"minecraft:melon":56,"minecraft:glass":124,"minecraft:sugar_cane":3,"minecraft:chain":1,"minecraft:wheat":355,"minecraft:lilac":3,"minecraft:oak_fence_gate":1,"minecraft:smooth_basalt":7,"minecraft:stonecutter":2,"minecraft:deepslate":514,"minecraft:attached_pumpkin_stem":3,"minecraft:dark_prismarine":10,"minecraft:mossy_cobblestone":46,"minecraft:dark_oak_log":3,"minecraft:shulker_box":1,"minecraft:end_stone":74,"minecraft:birch_fence_gate":2,"minecraft:nether_bricks":24,"minecraft:dark_oak_fence":3,"minecraft:spruce_fence":1,"minecraft:jungle_planks":337,"minecraft:kelp":1,"minecraft:redstone_ore":11,"minecraft:suspicious_sand":2,"minecraft:andesite":114,"minecraft:vine":46,"minecraft:rail":2,"minecraft:bamboo":65,"minecraft:white_wool":9,"minecraft:smithing_table":1,"minecraft:oak_slab":158,"minecraft:birch_stairs":99,"minecraft:stone_brick_slab":6,"minecraft:cobbled_deepslate_wall":5,"minecraft:short_grass":229,"minecraft:tall_grass":7,"minecraft:copper_ore":12,"minecraft:diorite":162,"minecraft:white_carpet":1,"minecraft:spruce_log":1,"minecraft:birch_leaves":5,"minecraft:gravel":1110,"minecraft:dripstone_block":4,"minecraft:cobweb":67,"minecraft:stone_bricks":13,"minecraft:chipped_anvil":1,"minecraft:fern":5,"minecraft:stone_pressure_plate":2,"minecraft:spruce_planks":32,"minecraft:farmland":204,"minecraft:jungle_slab":1,"minecraft:cobblestone_stairs":20,"minecraft:brewing_stand":2,"minecraft:grass_block":2877,"minecraft:cracked_polished_blackstone_bricks":5,"minecraft:iron_ore":47,"minecraft:dark_oak_stairs":17,"minecraft:pointed_dripstone":1,"minecraft:iron_bars":2,"minecraft:deepslate_redstone_ore":76,"minecraft:blackstone":93,"minecraft:melon_stem":15,"minecraft:jungle_stairs":1,"minecraft:poppy":1,"minecraft:chest":2,"minecraft:nether_quartz_ore":10,"minecraft:cobblestone":309,"minecraft:grindstone":2,"minecraft:prismarine":13,"minecraft:oak_planks":116,"minecraft:iron_door":4,"minecraft:wall_torch":2,"minecraft:pink_petals":1,"minecraft:yellow_wool":9,"minecraft:birch_log":3,"minecraft:birch_trapdoor":3,"minecraft:oak_log":96,"minecraft:beetroots":119,"minecraft:acacia_fence":2,"minecraft:sand":785,"minecraft:dirt":5653,"minecraft:netherrack":2773,"minecraft:ancient_debris":68,"minecraft:oak_leaves":176,"minecraft:nether_gold_ore":1,"minecraft:diamond_ore":9,"minecraft:tuff":34,"minecraft:deepslate_diamond_ore":271,"minecraft:oak_door":11,"minecraft:ladder":6,"minecraft:birch_slab":41,"minecraft:sandstone":30,"minecraft:hay_block":7,"minecraft:carrots":115,"minecraft:gold_block":16,"minecraft:nether_brick_fence":5,"minecraft:bookshelf":1,"minecraft:deepslate_iron_ore":168,"minecraft:shroomlight":1,"minecraft:wet_sponge":14,"minecraft:stone":7167,"minecraft:infested_stone_bricks":1,"minecraft:stripped_dark_oak_log":1,"minecraft:basalt":885,"minecraft:oak_fence":18,"minecraft:crafting_table":2,"minecraft:rose_bush":2,"minecraft:lapis_ore":8,"minecraft:polished_blackstone_brick_stairs":1,"minecraft:prismarine_bricks":28,"minecraft:spruce_stairs":9,"minecraft:birch_planks":520,"minecraft:coal_ore":395,"minecraft:cocoa":4,"minecraft:mossy_stone_bricks":1,"minecraft:birch_fence":10}},"DataVersion":3700}